rag_retrieval/__init__.py
rag_retrieval/reranker.py
rag_retrieval/infer/reranker_models/__init__.py
rag_retrieval/infer/reranker_models/colbert_ranker.py
rag_retrieval/infer/reranker_models/cross_encoder_ranker.py
rag_retrieval/infer/reranker_models/llm_rankers.py
rag_retrieval/infer/reranker_models/ranker.py
rag_retrieval/infer/reranker_models/result.py
rag_retrieval/infer/reranker_models/utils.py
rag_retrieval-0.2.2.dist-info/LICENSE
rag_retrieval-0.2.2.dist-info/METADATA
rag_retrieval-0.2.2.dist-info/WHEEL
rag_retrieval-0.2.2.dist-info/top_level.txt
rag_retrieval-0.2.2.dist-info/RECORD
