Metadata-Version: 2.1
Name: rag_retrieval
Version: 0.2.2
Summary: A unified API for various RAG Retrieval  reranker models.
Author-email: A grass in the car <suda.jcli@qq.com>
Maintainer-email: A grass in the car <suda.jcli@qq.com>
License: MIT License
Project-URL: Homepage, https://github.com/NLPJCL/RAG-Retrieval
Keywords: reranking,retrieval,rag,nlp
Classifier: Programming Language :: Python :: 3
Classifier: Programming Language :: Python :: 3.8
Classifier: Programming Language :: Python :: 3.9
Classifier: Programming Language :: Python :: 3.10
Classifier: Programming Language :: Python :: 3.11
Classifier: Programming Language :: Python :: 3.12
Classifier: Programming Language :: Python :: 3 :: Only
Requires-Python: >=3.8
License-File: LICENSE
Requires-Dist: pydantic
Requires-Dist: tqdm
Requires-Dist: torch
Requires-Dist: transformers
